groover/__init__.py
groover/classifier.py
groover/timepoints.py
groover/utils.py
groover-0.2.2.dist-info/METADATA
groover-0.2.2.dist-info/WHEEL
groover-0.2.2.dist-info/top_level.txt
groover-0.2.2.dist-info/RECORD
