Metadata-Version: 2.1
Name: groover
Version: 0.2.2
Summary: A rhythm feature extractor and classifier for MIDI files
Home-page: UNKNOWN
Author: Joshua Chang
Author-email: chchang6@illinois.edu
License: UNKNOWN
Platform: UNKNOWN
Classifier: Programming Language :: Python :: 3
Classifier: License :: OSI Approved :: MIT License
Classifier: Operating System :: OS Independent
Requires-Python: >=3.6
Requires-Dist: numpy
Requires-Dist: miditoolkit
